cfn_get_export_value/__init__.py
cfn_get_export_value/cfn_get_export_value.py
cfn_get_export_value-0.0.4.dist-info/LICENSE.txt
cfn_get_export_value-0.0.4.dist-info/METADATA
cfn_get_export_value-0.0.4.dist-info/WHEEL
cfn_get_export_value-0.0.4.dist-info/top_level.txt
cfn_get_export_value-0.0.4.dist-info/RECORD
