Metadata-Version: 2.1
Name: cfn-get-export-value
Version: 0.0.4
Summary: Get an exported value in AWS CloudFormation
Home-page: https://github.com/PokaInc/cfn-get-export-value
Author: Simon-Pierre Gingras
Author-email: spgingras@poka.io
License: UNKNOWN
Download-URL: https://github.com/PokaInc/cfn-get-export-value/tarball/0.0.4
Keywords: aws,cloudformation,exports
Platform: UNKNOWN
Requires-Dist: boto3
